{
    "scenes": [
        {
            "id": "AnubsAdultLs-1",
            "duration": 12
        },
        {
            "id": "AnubsAdultLs-2",
            "duration": 5.666667
        },
        {
            "id": "AnubsAdultLs-3",
            "duration": 5.6
        },
        {
            "id": "AnubsAdultLs-4",
            "duration": 6
        },
        {
            "id": "AnubsAdultLs-5",
            "duration": 5.133333
        },
        {
            "id": "AnubsAdultLs-6",
            "duration": 4.6
        }
    ],
    "tags": []
}