{
    "name": "Anubs FFM Femdom 3",
    "modpack": "AnubsAnimations",
    "length": 2,
    "navigations": [
        {
            "destination": "AnubsFfmFemdom3-4",
            "description": "Next(climax)",
            "icon": "OStim/symbols/climax"
        },
        {
            "destination": "AnubsFfmFemdom3-2",
            "description": "Back",
            "icon": "OStim/symbols/previous"
        },
        {
            "destination": "AnubsSpawnFurnitureFfmHub",
            "description": "Return",
            "icon": "OStim/symbols/return"
        },
        {
            "destination": "AnubsFfmFemdom3-3SwappedM0-F1",
            "description": "Rotate females",
            "icon": "OStim/symbols/rotate_cw"
        }
    ],
    "speeds": [
        {
            "animation": "AnubsFfmFemdom3_3"
        }
    ],
    "actors": [
        {
            "intendedSex": "male",
            "sosBend": 0,
            "scale": 1,
            "feetOnGround": true,
            "tags": [
                "squatting"
            ],
            "autoTransitions": {
                "climax": "AnubsFfmFemdom3-4"
            }
        },
        {
            "intendedSex": "female",
            "scale": 1,
            "feetOnGround": true,
            "tags": [
                "sitting"
            ]
        },
        {
            "intendedSex": "female",
            "scale": 1,
            "feetOnGround": false,
            "tags": [
                "sitting"
            ]
        }
    ],
    "actions": [
        {
            "type": "vaginalsex",
            "actor": 0,
            "target": 2,
            "performer": 2
        },
        {
            "type": "femalemasturbation",
            "actor": 1
        }
    ],
    "noRandomSelection": true,
    "tags": [
        "anubs"
    ]
}